simple/__init__.py
simple/__version__.py
simple/ccsne.py
simple/models.py
simple/norm.py
simple/plotting.py
simple/roseaxes.py
simple/utils.py
simple_chetec-0.4.3.dist-info/licenses/LICENSE.md
simple_chetec-0.4.3.dist-info/METADATA
simple_chetec-0.4.3.dist-info/WHEEL
simple_chetec-0.4.3.dist-info/top_level.txt
simple_chetec-0.4.3.dist-info/RECORD
