Metadata-Version: 2.4
Name: simple-chetec
Version: 0.4.3
Summary: Stellar Interpretation for Meteoritic data and PLotting (for Everyone)
Author-email: Mattias Ek <mattias.ek@pm.me>
License-Expression: LGPL-3.0-or-later
Requires-Python: >=3.9
License-File: LICENSE.md
Requires-Dist: numpy>=1.22
Requires-Dist: matplotlib>=3.5
Requires-Dist: scipy>=1.8
Requires-Dist: h5py>=3.6
Requires-Dist: pyyaml>=5.4
Provides-Extra: dev
Requires-Dist: ipykernel; extra == "dev"
Requires-Dist: nugridpy; extra == "dev"
Requires-Dist: pytest; extra == "dev"
Requires-Dist: pytest-cov; extra == "dev"
Requires-Dist: coverage[toml]; extra == "dev"
Requires-Dist: nox; extra == "dev"
Provides-Extra: test
Requires-Dist: pytest; extra == "test"
Requires-Dist: pytest-cov; extra == "test"
Requires-Dist: coverage[toml]; extra == "test"
Provides-Extra: docs
Requires-Dist: mkdocs==1.6.1; extra == "docs"
Requires-Dist: mkdocs-material; extra == "docs"
Requires-Dist: mkdocstrings==0.26.1; extra == "docs"
Requires-Dist: mkdocstrings-python==1.11.1; extra == "docs"
Requires-Dist: mkdocs-gen-files; extra == "docs"
Requires-Dist: mkdocs-jupyter==0.25; extra == "docs"
Requires-Dist: pymdown-extensions; extra == "docs"
Dynamic: license-file
